README
setup.py
django_mailchimp_forms/__init__.py
django_mailchimp_forms/admin.py
django_mailchimp_forms/forms.py
django_mailchimp_forms/models.py
django_mailchimp_forms/tests.py
django_mailchimp_forms/urls.py
django_mailchimp_forms/utils.py
django_mailchimp_forms/views.py
django_mailchimp_forms.egg-info/PKG-INFO
django_mailchimp_forms.egg-info/SOURCES.txt
django_mailchimp_forms.egg-info/dependency_links.txt
django_mailchimp_forms.egg-info/not-zip-safe
django_mailchimp_forms.egg-info/requires.txt
django_mailchimp_forms.egg-info/top_level.txt