Metadata-Version: 1.0
Name: django-mailchimp-forms
Version: 0.2
Summary: Mailchimp registration framework for Django
Home-page: http://code.indifex.com/django-mailchimp-forms/
Author: Konstantinos Bairaktaris
Author-email: kbairak@indifex.com
License: BSD
Download-URL: http://code.indifex.com/django-mailchimp-forms/downloads/
Platform: UNKNOWN
Classifier: Development Status :: 4 - Beta
Classifier: Environment :: Web Environment
Classifier: Framework :: Django
Classifier: Intended Audience :: Developers
Classifier: License :: OSI Approved :: BSD License
Classifier: Operating System :: OS Independent
Classifier: Programming Language :: Python
Classifier: Topic :: Software Development :: Libraries :: Python Modules
Classifier: Topic :: Utilities
